fastdto/__init__.py
fastdto/__main__.py
fastdto/cli/__init__.py
fastdto/cli/cli.py
fastdto/common/__init__.py
fastdto/common/dto.py
fastdto/common/enums.py
fastdto/common/errors.py
fastdto/common/mappings.py
fastdto/common/utils.py
fastdto/connection/__init__.py
fastdto/connection/interface.py
fastdto/connection/sqlalchemy.py
fastdto/core/__init__.py
fastdto/core/codegen/__init__.py
fastdto/core/codegen/model.py
fastdto/core/codegen/service.py
fastdto/core/dsl/__init__.py
fastdto/core/dsl/parse/__init__.py
fastdto/core/dsl/parse/service.py
fastdto/core/dsl/schema/__init__.py
fastdto/core/dsl/schema/base.py
fastdto/core/dsl/schema/column.py
fastdto/templates/init/README.md
fastdto/templates/init/dbschema.py
fastdto-0.2.0.dist-info/LICENSE
fastdto-0.2.0.dist-info/METADATA
fastdto-0.2.0.dist-info/WHEEL
fastdto-0.2.0.dist-info/entry_points.txt
fastdto-0.2.0.dist-info/RECORD
